easyimages/Verdana.ttf
easyimages/__init__.py
easyimages/easyimages.py
easyimages/imgcat.txt
easyimages/logger.py
easyimages/utils.py
easyimages-1.91.dist-info/AUTHORS.rst
easyimages-1.91.dist-info/LICENSE
easyimages-1.91.dist-info/METADATA
easyimages-1.91.dist-info/WHEEL
easyimages-1.91.dist-info/top_level.txt
easyimages-1.91.dist-info/RECORD
