Metadata-Version: 2.1
Name: easyimages
Version: 1.91
Summary: Images made easy
Home-page: https://github.com/i008/easyimages
Author: Jakub Cieslik
Author-email: kubacieslik@gmail.com
License: MIT license
Keywords: easyimages
Platform: UNKNOWN
Classifier: Development Status :: 2 - Pre-Alpha
Classifier: Intended Audience :: Developers
Classifier: License :: OSI Approved :: MIT License
Classifier: Natural Language :: English
Classifier: Programming Language :: Python :: 3.6
Classifier: Programming Language :: Python :: 3.7
Requires-Dist: cython
Requires-Dist: imutils (==0.4.6)
Requires-Dist: matplotlib
Requires-Dist: requests (>=2.11.1)
Requires-Dist: numpy (>=1.14.5)
Requires-Dist: ipython
Requires-Dist: Pillow (>=5.2.0)
Requires-Dist: opencv-python
Requires-Dist: ipywidgets
Requires-Dist: pycocotools
Requires-Dist: pytest
